LICENSE
MANIFEST.in
README.md
name_tests.py
nameparts.py
setup.py
nameparts.egg-info/PKG-INFO
nameparts.egg-info/SOURCES.txt
nameparts.egg-info/dependency_links.txt
nameparts.egg-info/top_level.txt