Metadata-Version: 1.0
Name: nameparts
Version: 0.5.4
Summary: Takes a full human name and splits it into individual parts
Home-page: https://github.com/polera/nameparts
Author: James Polera
Author-email: james@uncryptic.com
License: BSD
Keywords: name,text,processing
Platform: UNKNOWN
Classifier: Development Status :: 5 - Production/Stable
Classifier: Intended Audience :: Developers
Classifier: Natural Language :: English
Classifier: License :: OSI Approved :: BSD License
Classifier: Programming Language :: Python
Classifier: Programming Language :: Python :: 2.6
Classifier: Programming Language :: Python :: 2.7
Classifier: Programming Language :: Python :: 3.2
